{
  "stats": {
    "suites": 1,
    "tests": 1,
    "passes": 1,
    "pending": 0,
    "failures": 0,
    "start": "2022-01-13T21:03:20.025Z",
    "end": "2022-01-13T21:03:20.470Z",
    "duration": 445
  },
  "tests": [
    {
      "title": "exists",
      "fullTitle": "index.js exists",
      "duration": 1,
      "currentRetry": 0,
      "err": {}
    }
  ],
  "pending": [],
  "failures": [],
  "passes": [
    {
      "title": "exists",
      "fullTitle": "index.js exists",
      "duration": 1,
      "currentRetry": 0,
      "err": {}
    }
  ]
}